selfclean/__init__.py
selfclean/cleaner/__init__.py
selfclean/cleaner/auto_cleaning_mixin.py
selfclean/cleaner/base_cleaner.py
selfclean/cleaner/issue_manager.py
selfclean/cleaner/selfclean.py
selfclean/cleaner/selfclean_cleaner.py
selfclean/cleaner/label_errors/__init__.py
selfclean/cleaner/label_errors/base_label_error_mixin.py
selfclean/cleaner/label_errors/intra_extra_distance_mixin.py
selfclean/cleaner/near_duplicates/__init__.py
selfclean/cleaner/near_duplicates/base_near_duplicate_mixin.py
selfclean/cleaner/near_duplicates/embedding_distance_mixin.py
selfclean/cleaner/off_topic_samples/__init__.py
selfclean/cleaner/off_topic_samples/base_off_topic_mixin.py
selfclean/cleaner/off_topic_samples/lad_mixin.py
selfclean/cleaner/off_topic_samples/quantile_off_topic_mixin.py
selfclean/core/__init__.py
selfclean/core/src/__init__.py
selfclean/core/src/augmentations/__init__.py
selfclean/core/src/augmentations/augmentations.py
selfclean/core/src/augmentations/multi_crop.py
selfclean/core/src/augmentations/simclr.py
selfclean/core/src/dataset_wrappers/__init__.py
selfclean/core/src/dataset_wrappers/base_wrapper.py
selfclean/core/src/dataset_wrappers/colorme_wrapper.py
selfclean/core/src/dataset_wrappers/ibot_wrapper.py
selfclean/core/src/datasets/__init__.py
selfclean/core/src/datasets/base_dataset.py
selfclean/core/src/datasets/encrypted_image_dataset.py
selfclean/core/src/datasets/generic_image_dataset.py
selfclean/core/src/datasets/helper.py
selfclean/core/src/datasets/image_text_dataset.py
selfclean/core/src/datasets/utils.py
selfclean/core/src/datasets/downstream_tasks/__init__.py
selfclean/core/src/datasets/downstream_tasks/celeba_dataset.py
selfclean/core/src/datasets/downstream_tasks/chest_xray_covid_dataset.py
selfclean/core/src/datasets/downstream_tasks/chexpert_dataset.py
selfclean/core/src/datasets/downstream_tasks/ddi_dataset.py
selfclean/core/src/datasets/downstream_tasks/derm7pt_dataset.py
selfclean-0.0.36.dist-info/LICENSE.md
selfclean-0.0.36.dist-info/METADATA
selfclean-0.0.36.dist-info/WHEEL
selfclean-0.0.36.dist-info/top_level.txt
selfclean-0.0.36.dist-info/RECORD
