Metadata-Version: 2.2
Name: selfclean
Version: 0.0.36
Summary: A holistic self-supervised data cleaning strategy to detect off-topic samples, near duplicates and label errors.
Author-email: Fabian Gröger <fabian.groeger@unibas.ch>
License: Attribution-NonCommercial 4.0 International
Project-URL: Homepage, https://selfclean.github.io/
Project-URL: Source Code, https://github.com/Digital-Dermatology/SelfClean
Keywords: machine_learning,data_cleaning,datacentric_ai,datacentric,self-supervised learning
Classifier: Programming Language :: Python :: 3
Classifier: Operating System :: OS Independent
Requires-Python: >=3.6
License-File: LICENSE.md
Requires-Dist: SciencePlots
Requires-Dist: black>=22.6
Requires-Dist: codecov
Requires-Dist: coverage>=6
Requires-Dist: darglint>=1.8
Requires-Dist: einops
Requires-Dist: isort>=5.10
Requires-Dist: jupyter
Requires-Dist: loguru
Requires-Dist: matplotlib
Requires-Dist: memory-profiler
Requires-Dist: numpy
Requires-Dist: pandas
Requires-Dist: pre-commit>=2.20
Requires-Dist: pytest
Requires-Dist: pytest-cov>=3
Requires-Dist: scikit-image
Requires-Dist: scikit_learn
Requires-Dist: seaborn
Requires-Dist: torchinfo
Requires-Dist: torchmetrics
Requires-Dist: torchvision
Requires-Dist: tqdm
Requires-Dist: transformers[torch]==4.27.4
Provides-Extra: approximate-nn
Requires-Dist: annoy; extra == "approximate-nn"
